env_config/__init__.py
env_config/base.py
env_config/constants.py
env_config/decorators.py
env_config/errors.py
env_config/py.typed
env_config/typing.py
env_config/values.py
env_config_pytest_plugin/__init__.py
env_config_pytest_plugin/hooks.py
django_environment_config-0.2.3.dist-info/LICENSE
django_environment_config-0.2.3.dist-info/METADATA
django_environment_config-0.2.3.dist-info/WHEEL
django_environment_config-0.2.3.dist-info/entry_points.txt
django_environment_config-0.2.3.dist-info/RECORD
