Metadata-Version: 2.3
Name: django-environment-config
Version: 0.2.3
Summary: Configure django settings for multiple environments.
Home-page: https://mrthearman.github.io/django-environment-config
License: MIT
Keywords: django,configuration,settings,environment,env,config
Author: Matti Lamppu
Author-email: lamppu.matti.akseli@gmail.com
Requires-Python: >=3.10,<4
Classifier: Environment :: Web Environment
Classifier: Operating System :: OS Independent
Classifier: Intended Audience :: Developers
Classifier: Natural Language :: English
Classifier: Programming Language :: Python
Classifier: Programming Language :: Python :: 3
Classifier: Programming Language :: Python :: 3 :: Only
Classifier: Programming Language :: Python :: 3.10
Classifier: Programming Language :: Python :: 3.11
Classifier: Programming Language :: Python :: 3.12
Classifier: Programming Language :: Python :: 3.13
Classifier: Framework :: Django :: 4.2
Classifier: Framework :: Django :: 5.0
Classifier: Framework :: Django :: 5.1
Classifier: Framework :: Django :: 5.2
Provides-Extra: cache
Provides-Extra: db
Requires-Dist: Django (>=4.2)
Requires-Dist: dj-database-url (>=2.3.0) ; extra == "db"
Requires-Dist: django-cache-url (>=3.4.5) ; extra == "cache"
Requires-Dist: python-dotenv (>=1.1.1)
Requires-Dist: typing-extensions (>=4.11.0) ; python_version < "3.12"
Project-URL: Bug Tracker, https://github.com/MrThearMan/django-environment-config/issues
Project-URL: Documentation, https://mrthearman.github.io/django-environment-config
Project-URL: Repository, https://github.com/MrThearMan/django-environment-config
